[
 {
  "docstatus": 0,
  "doctype": "Workflow",
  "document_type": "Project",
  "is_active": 1,
  "modified": "2021-10-27 16:12:02.405217",
  "name": "Project Workflow",
  "override_status": 0,
  "parent": null,
  "parentfield": null,
  "parenttype": null,
  "send_email_alert": 1,
  "states": [
   {
    "allow_edit": "Projects User",
    "doc_status": "0",
    "is_optional_state": 0,
    "message": null,
    "next_action_email_template": null,
    "parent": "Project Workflow",
    "parentfield": "states",
    "parenttype": "Workflow",
    "state": "Draft",
    "update_field": null,
    "update_value": null
   },
   {
    "allow_edit": "Sales Manager",
    "doc_status": "0",
    "is_optional_state": 0,
    "message": null,
    "next_action_email_template": null,
    "parent": "Project Workflow",
    "parentfield": "states",
    "parenttype": "Workflow",
    "state": "Released for Authorization",
    "update_field": null,
    "update_value": null
   },
   {
    "allow_edit": "System Manager",
    "doc_status": "0",
    "is_optional_state": 0,
    "message": null,
    "next_action_email_template": null,
    "parent": "Project Workflow",
    "parentfield": "states",
    "parenttype": "Workflow",
    "state": "Authorized",
    "update_field": null,
    "update_value": null
   }
  ],
  "transitions": [
   {
    "action": "Send For Authorisation",
    "allow_self_approval": 1,
    "allowed": "Projects User",
    "condition": null,
    "next_state": "Released for Authorization",
    "parent": "Project Workflow",
    "parentfield": "transitions",
    "parenttype": "Workflow",
    "state": "Draft"
   },
   {
    "action": "Approve",
    "allow_self_approval": 1,
    "allowed": "Sales Manager",
    "condition": "doc.sales_order",
    "next_state": "Authorized",
    "parent": "Project Workflow",
    "parentfield": "transitions",
    "parenttype": "Workflow",
    "state": "Released for Authorization"
   },
   {
    "action": "Reject",
    "allow_self_approval": 1,
    "allowed": "Sales Manager",
    "condition": null,
    "next_state": "Draft",
    "parent": "Project Workflow",
    "parentfield": "transitions",
    "parenttype": "Workflow",
    "state": "Released for Authorization"
   },
   {
    "action": "Approve",
    "allow_self_approval": 1,
    "allowed": "Managing Director",
    "condition": null,
    "next_state": "Authorized",
    "parent": "Project Workflow",
    "parentfield": "transitions",
    "parenttype": "Workflow",
    "state": "Released for Authorization"
   }
  ],
  "workflow_name": "Project Workflow",
  "workflow_state_field": "workflow_state"
 },
 {
  "docstatus": 0,
  "doctype": "Workflow",
  "document_type": "Stock Entry",
  "is_active": 1,
  "modified": "2021-11-20 14:40:27.888898",
  "name": "Stock Entry Authorisation",
  "override_status": 0,
  "parent": "Stock Entry",
  "parentfield": null,
  "parenttype": null,
  "send_email_alert": 0,
  "states": [
   {
    "allow_edit": "Manufacturing User",
    "doc_status": "0",
    "is_optional_state": 0,
    "message": null,
    "next_action_email_template": null,
    "parent": "Stock Entry Authorisation",
    "parentfield": "states",
    "parenttype": "Workflow",
    "state": "Draft",
    "update_field": null,
    "update_value": null
   },
   {
    "allow_edit": "Manufacturing Manager",
    "doc_status": "0",
    "is_optional_state": 0,
    "message": null,
    "next_action_email_template": null,
    "parent": "Stock Entry Authorisation",
    "parentfield": "states",
    "parenttype": "Workflow",
    "state": "Draft",
    "update_field": null,
    "update_value": null
   },
   {
    "allow_edit": "Guard",
    "doc_status": "0",
    "is_optional_state": 0,
    "message": null,
    "next_action_email_template": null,
    "parent": "Stock Entry Authorisation",
    "parentfield": "states",
    "parenttype": "Workflow",
    "state": "Authorisation Pending",
    "update_field": null,
    "update_value": null
   },
   {
    "allow_edit": "Projects Manager",
    "doc_status": "0",
    "is_optional_state": 0,
    "message": null,
    "next_action_email_template": null,
    "parent": "Stock Entry Authorisation",
    "parentfield": "states",
    "parenttype": "Workflow",
    "state": "Authorisation Pending",
    "update_field": null,
    "update_value": null
   },
   {
    "allow_edit": "Manufacturing User",
    "doc_status": "0",
    "is_optional_state": 0,
    "message": null,
    "next_action_email_template": null,
    "parent": "Stock Entry Authorisation",
    "parentfield": "states",
    "parenttype": "Workflow",
    "state": "Authorised",
    "update_field": null,
    "update_value": null
   },
   {
    "allow_edit": "Manufacturing User",
    "doc_status": "1",
    "is_optional_state": 0,
    "message": null,
    "next_action_email_template": null,
    "parent": "Stock Entry Authorisation",
    "parentfield": "states",
    "parenttype": "Workflow",
    "state": "Received",
    "update_field": null,
    "update_value": null
   },
   {
    "allow_edit": "Head Cutting Master",
    "doc_status": "1",
    "is_optional_state": 0,
    "message": null,
    "next_action_email_template": null,
    "parent": "Stock Entry Authorisation",
    "parentfield": "states",
    "parenttype": "Workflow",
    "state": "Received",
    "update_field": null,
    "update_value": null
   },
   {
    "allow_edit": "Manufacturing Manager",
    "doc_status": "1",
    "is_optional_state": 0,
    "message": null,
    "next_action_email_template": null,
    "parent": "Stock Entry Authorisation",
    "parentfield": "states",
    "parenttype": "Workflow",
    "state": "Approved",
    "update_field": null,
    "update_value": null
   },
   {
    "allow_edit": "Manufacturing Manager",
    "doc_status": "2",
    "is_optional_state": 0,
    "message": null,
    "next_action_email_template": null,
    "parent": "Stock Entry Authorisation",
    "parentfield": "states",
    "parenttype": "Workflow",
    "state": "Rejected",
    "update_field": null,
    "update_value": null
   },
   {
    "allow_edit": "System Manager",
    "doc_status": "2",
    "is_optional_state": 0,
    "message": null,
    "next_action_email_template": null,
    "parent": "Stock Entry Authorisation",
    "parentfield": "states",
    "parenttype": "Workflow",
    "state": "Rejected",
    "update_field": null,
    "update_value": null
   }
  ],
  "transitions": [
   {
    "action": "Send For Authorisation",
    "allow_self_approval": 1,
    "allowed": "Manufacturing User",
    "condition": "",
    "next_state": "Authorisation Pending",
    "parent": "Stock Entry Authorisation",
    "parentfield": "transitions",
    "parenttype": "Workflow",
    "state": "Draft"
   },
   {
    "action": "Authorise",
    "allow_self_approval": 1,
    "allowed": "Guard",
    "condition": "",
    "next_state": "Authorised",
    "parent": "Stock Entry Authorisation",
    "parentfield": "transitions",
    "parenttype": "Workflow",
    "state": "Authorisation Pending"
   },
   {
    "action": "Authorise",
    "allow_self_approval": 1,
    "allowed": "Projects Manager",
    "condition": null,
    "next_state": "Authorised",
    "parent": "Stock Entry Authorisation",
    "parentfield": "transitions",
    "parenttype": "Workflow",
    "state": "Authorisation Pending"
   },
   {
    "action": "Need Changes",
    "allow_self_approval": 1,
    "allowed": "Manufacturing Manager",
    "condition": null,
    "next_state": "Draft",
    "parent": "Stock Entry Authorisation",
    "parentfield": "transitions",
    "parenttype": "Workflow",
    "state": "Authorisation Pending"
   },
   {
    "action": "Receive",
    "allow_self_approval": 1,
    "allowed": "Manufacturing User",
    "condition": "",
    "next_state": "Received",
    "parent": "Stock Entry Authorisation",
    "parentfield": "transitions",
    "parenttype": "Workflow",
    "state": "Authorised"
   },
   {
    "action": "Receive",
    "allow_self_approval": 1,
    "allowed": "Head Cutting Master",
    "condition": "doc.project!=\"\"",
    "next_state": "Received",
    "parent": "Stock Entry Authorisation",
    "parentfield": "transitions",
    "parenttype": "Workflow",
    "state": "Authorised"
   },
   {
    "action": "Need Changes",
    "allow_self_approval": 1,
    "allowed": "Manufacturing Manager",
    "condition": null,
    "next_state": "Draft",
    "parent": "Stock Entry Authorisation",
    "parentfield": "transitions",
    "parenttype": "Workflow",
    "state": "Authorised"
   },
   {
    "action": "Reject",
    "allow_self_approval": 1,
    "allowed": "Manufacturing Manager",
    "condition": "",
    "next_state": "Rejected",
    "parent": "Stock Entry Authorisation",
    "parentfield": "transitions",
    "parenttype": "Workflow",
    "state": "Received"
   },
   {
    "action": "Reject",
    "allow_self_approval": 1,
    "allowed": "System Manager",
    "condition": null,
    "next_state": "Rejected",
    "parent": "Stock Entry Authorisation",
    "parentfield": "transitions",
    "parenttype": "Workflow",
    "state": "Received"
   },
   {
    "action": "Reject",
    "allow_self_approval": 1,
    "allowed": "Manufacturing Manager",
    "condition": null,
    "next_state": "Rejected",
    "parent": "Stock Entry Authorisation",
    "parentfield": "transitions",
    "parenttype": "Workflow",
    "state": "Approved"
   }
  ],
  "workflow_name": "Stock Entry Authorisation",
  "workflow_state_field": "workflow_state"
 },
 {
  "docstatus": 0,
  "doctype": "Workflow",
  "document_type": "Quotation",
  "is_active": 0,
  "modified": "2020-06-15 08:30:20.515385",
  "name": "Quotation Approval",
  "override_status": 0,
  "parent": null,
  "parentfield": null,
  "parenttype": null,
  "send_email_alert": 0,
  "states": [
   {
    "allow_edit": "Sales User",
    "doc_status": "0",
    "is_optional_state": 0,
    "message": null,
    "next_action_email_template": null,
    "parent": "Quotation Approval",
    "parentfield": "states",
    "parenttype": "Workflow",
    "state": "Draft",
    "update_field": null,
    "update_value": null
   },
   {
    "allow_edit": "Sales Manager",
    "doc_status": "0",
    "is_optional_state": 0,
    "message": null,
    "next_action_email_template": null,
    "parent": "Quotation Approval",
    "parentfield": "states",
    "parenttype": "Workflow",
    "state": "Pending",
    "update_field": null,
    "update_value": null
   },
   {
    "allow_edit": "Sales User",
    "doc_status": "0",
    "is_optional_state": 0,
    "message": null,
    "next_action_email_template": null,
    "parent": "Quotation Approval",
    "parentfield": "states",
    "parenttype": "Workflow",
    "state": "Rejected",
    "update_field": null,
    "update_value": null
   },
   {
    "allow_edit": "Sales Manager",
    "doc_status": "1",
    "is_optional_state": 0,
    "message": null,
    "next_action_email_template": null,
    "parent": "Quotation Approval",
    "parentfield": "states",
    "parenttype": "Workflow",
    "state": "Approved",
    "update_field": null,
    "update_value": null
   }
  ],
  "transitions": [
   {
    "action": "Send For Authorisation",
    "allow_self_approval": 1,
    "allowed": "Sales User",
    "condition": null,
    "next_state": "Pending",
    "parent": "Quotation Approval",
    "parentfield": "transitions",
    "parenttype": "Workflow",
    "state": "Draft"
   },
   {
    "action": "Authorise",
    "allow_self_approval": 1,
    "allowed": "Sales Manager",
    "condition": null,
    "next_state": "Approved",
    "parent": "Quotation Approval",
    "parentfield": "transitions",
    "parenttype": "Workflow",
    "state": "Pending"
   },
   {
    "action": "Reject",
    "allow_self_approval": 1,
    "allowed": "Sales Manager",
    "condition": null,
    "next_state": "Rejected",
    "parent": "Quotation Approval",
    "parentfield": "transitions",
    "parenttype": "Workflow",
    "state": "Pending"
   },
   {
    "action": "Send For Authorisation",
    "allow_self_approval": 1,
    "allowed": "Sales User",
    "condition": null,
    "next_state": "Pending",
    "parent": "Quotation Approval",
    "parentfield": "transitions",
    "parenttype": "Workflow",
    "state": "Rejected"
   }
  ],
  "workflow_name": "Quotation Approval",
  "workflow_state_field": "workflow_state"
 },
 {
  "docstatus": 0,
  "doctype": "Workflow",
  "document_type": "Purchase Receipt",
  "is_active": 1,
  "modified": "2021-01-25 18:47:23.796517",
  "name": "Purchase Receipt Apporoval",
  "override_status": 0,
  "parent": null,
  "parentfield": null,
  "parenttype": null,
  "send_email_alert": 0,
  "states": [
   {
    "allow_edit": "Purchase User",
    "doc_status": "0",
    "is_optional_state": 0,
    "message": null,
    "next_action_email_template": null,
    "parent": "Purchase Receipt Apporoval",
    "parentfield": "states",
    "parenttype": "Workflow",
    "state": "Draft",
    "update_field": null,
    "update_value": null
   },
   {
    "allow_edit": "Stock User",
    "doc_status": "0",
    "is_optional_state": 0,
    "message": null,
    "next_action_email_template": null,
    "parent": "Purchase Receipt Apporoval",
    "parentfield": "states",
    "parenttype": "Workflow",
    "state": "Pending",
    "update_field": null,
    "update_value": null
   },
   {
    "allow_edit": "Stock User",
    "doc_status": "0",
    "is_optional_state": 0,
    "message": null,
    "next_action_email_template": null,
    "parent": "Purchase Receipt Apporoval",
    "parentfield": "states",
    "parenttype": "Workflow",
    "state": "Authorised",
    "update_field": null,
    "update_value": null
   },
   {
    "allow_edit": "Stock Manager",
    "doc_status": "0",
    "is_optional_state": 0,
    "message": null,
    "next_action_email_template": null,
    "parent": "Purchase Receipt Apporoval",
    "parentfield": "states",
    "parenttype": "Workflow",
    "state": "Rejected",
    "update_field": null,
    "update_value": null
   },
   {
    "allow_edit": "Stock Manager",
    "doc_status": "1",
    "is_optional_state": 0,
    "message": null,
    "next_action_email_template": null,
    "parent": "Purchase Receipt Apporoval",
    "parentfield": "states",
    "parenttype": "Workflow",
    "state": "Approved",
    "update_field": null,
    "update_value": null
   },
   {
    "allow_edit": "Stock Manager",
    "doc_status": "2",
    "is_optional_state": 0,
    "message": null,
    "next_action_email_template": null,
    "parent": "Purchase Receipt Apporoval",
    "parentfield": "states",
    "parenttype": "Workflow",
    "state": "Cancelled",
    "update_field": null,
    "update_value": null
   }
  ],
  "transitions": [
   {
    "action": "Send For Authorisation",
    "allow_self_approval": 1,
    "allowed": "Purchase User",
    "condition": null,
    "next_state": "Pending",
    "parent": "Purchase Receipt Apporoval",
    "parentfield": "transitions",
    "parenttype": "Workflow",
    "state": "Draft"
   },
   {
    "action": "Authorise",
    "allow_self_approval": 1,
    "allowed": "Stock User",
    "condition": null,
    "next_state": "Authorised",
    "parent": "Purchase Receipt Apporoval",
    "parentfield": "transitions",
    "parenttype": "Workflow",
    "state": "Pending"
   },
   {
    "action": "Approve",
    "allow_self_approval": 1,
    "allowed": "Stock Manager",
    "condition": null,
    "next_state": "Approved",
    "parent": "Purchase Receipt Apporoval",
    "parentfield": "transitions",
    "parenttype": "Workflow",
    "state": "Authorised"
   },
   {
    "action": "Reject",
    "allow_self_approval": 1,
    "allowed": "Stock Manager",
    "condition": null,
    "next_state": "Rejected",
    "parent": "Purchase Receipt Apporoval",
    "parentfield": "transitions",
    "parenttype": "Workflow",
    "state": "Authorised"
   },
   {
    "action": "Send For Authorisation",
    "allow_self_approval": 1,
    "allowed": "Stock Manager",
    "condition": null,
    "next_state": "Pending",
    "parent": "Purchase Receipt Apporoval",
    "parentfield": "transitions",
    "parenttype": "Workflow",
    "state": "Rejected"
   },
   {
    "action": "Cancel",
    "allow_self_approval": 1,
    "allowed": "Stock Manager",
    "condition": null,
    "next_state": "Cancelled",
    "parent": "Purchase Receipt Apporoval",
    "parentfield": "transitions",
    "parenttype": "Workflow",
    "state": "Approved"
   }
  ],
  "workflow_name": "Purchase Receipt Apporoval",
  "workflow_state_field": "workflow_state"
 },
 {
  "docstatus": 0,
  "doctype": "Workflow",
  "document_type": "Item Price",
  "is_active": 1,
  "modified": "2020-08-17 10:59:08.508998",
  "name": "Item Price",
  "override_status": 0,
  "parent": null,
  "parentfield": null,
  "parenttype": null,
  "send_email_alert": 0,
  "states": [
   {
    "allow_edit": "Manufacturing User",
    "doc_status": "0",
    "is_optional_state": 0,
    "message": null,
    "next_action_email_template": null,
    "parent": "Item Price",
    "parentfield": "states",
    "parenttype": "Workflow",
    "state": "Draft",
    "update_field": null,
    "update_value": null
   },
   {
    "allow_edit": "Managing Director",
    "doc_status": "0",
    "is_optional_state": 0,
    "message": null,
    "next_action_email_template": null,
    "parent": "Item Price",
    "parentfield": "states",
    "parenttype": "Workflow",
    "state": "Authorisation Pending",
    "update_field": null,
    "update_value": null
   },
   {
    "allow_edit": "Managing Director",
    "doc_status": "0",
    "is_optional_state": 0,
    "message": null,
    "next_action_email_template": null,
    "parent": "Item Price",
    "parentfield": "states",
    "parenttype": "Workflow",
    "state": "Approved",
    "update_field": null,
    "update_value": null
   }
  ],
  "transitions": [
   {
    "action": "Send For Authorisation",
    "allow_self_approval": 1,
    "allowed": "Manufacturing User",
    "condition": null,
    "next_state": "Authorisation Pending",
    "parent": "Item Price",
    "parentfield": "transitions",
    "parenttype": "Workflow",
    "state": "Draft"
   },
   {
    "action": "Authorise",
    "allow_self_approval": 1,
    "allowed": "Managing Director",
    "condition": null,
    "next_state": "Approved",
    "parent": "Item Price",
    "parentfield": "transitions",
    "parenttype": "Workflow",
    "state": "Authorisation Pending"
   }
  ],
  "workflow_name": "Item Price",
  "workflow_state_field": "workflow_state"
 },
 {
  "docstatus": 0,
  "doctype": "Workflow",
  "document_type": "Payment Entry",
  "is_active": 0,
  "modified": "2021-01-28 16:27:07.407330",
  "name": "Payment Request",
  "override_status": 0,
  "parent": null,
  "parentfield": null,
  "parenttype": null,
  "send_email_alert": 1,
  "states": [
   {
    "allow_edit": "Accounts User",
    "doc_status": "0",
    "is_optional_state": 0,
    "message": null,
    "next_action_email_template": null,
    "parent": "Payment Request",
    "parentfield": "states",
    "parenttype": "Workflow",
    "state": "Draft",
    "update_field": null,
    "update_value": null
   },
   {
    "allow_edit": "Accounts User",
    "doc_status": "0",
    "is_optional_state": 0,
    "message": null,
    "next_action_email_template": null,
    "parent": "Payment Request",
    "parentfield": "states",
    "parenttype": "Workflow",
    "state": "Request for Release",
    "update_field": null,
    "update_value": null
   },
   {
    "allow_edit": "System Manager",
    "doc_status": "1",
    "is_optional_state": 0,
    "message": null,
    "next_action_email_template": null,
    "parent": "Payment Request",
    "parentfield": "states",
    "parenttype": "Workflow",
    "state": "Paid",
    "update_field": null,
    "update_value": null
   },
   {
    "allow_edit": "System Manager",
    "doc_status": "2",
    "is_optional_state": 0,
    "message": null,
    "next_action_email_template": null,
    "parent": "Payment Request",
    "parentfield": "states",
    "parenttype": "Workflow",
    "state": "Cancelled",
    "update_field": null,
    "update_value": null
   }
  ],
  "transitions": [
   {
    "action": "Release",
    "allow_self_approval": 1,
    "allowed": "Accounts User",
    "condition": "doc.payment_type == \"Pay\"",
    "next_state": "Request for Release",
    "parent": "Payment Request",
    "parentfield": "transitions",
    "parenttype": "Workflow",
    "state": "Draft"
   },
   {
    "action": "Pay",
    "allow_self_approval": 1,
    "allowed": "System Manager",
    "condition": "doc.payment_type == \"Pay\"",
    "next_state": "Paid",
    "parent": "Payment Request",
    "parentfield": "transitions",
    "parenttype": "Workflow",
    "state": "Request for Release"
   },
   {
    "action": "Cancel",
    "allow_self_approval": 1,
    "allowed": "System Manager",
    "condition": "doc.payment_type == \"Pay\"",
    "next_state": "Cancelled",
    "parent": "Payment Request",
    "parentfield": "transitions",
    "parenttype": "Workflow",
    "state": "Paid"
   }
  ],
  "workflow_name": "Payment Request",
  "workflow_state_field": "workflow_state"
 },
 {
  "docstatus": 0,
  "doctype": "Workflow",
  "document_type": "Event",
  "is_active": 1,
  "modified": "2021-02-16 16:51:20.942365",
  "name": "Event Approval",
  "override_status": 0,
  "parent": null,
  "parentfield": null,
  "parenttype": null,
  "send_email_alert": 1,
  "states": [
   {
    "allow_edit": "System Manager",
    "doc_status": "0",
    "is_optional_state": 0,
    "message": null,
    "next_action_email_template": null,
    "parent": "Event Approval",
    "parentfield": "states",
    "parenttype": "Workflow",
    "state": "Pending",
    "update_field": null,
    "update_value": null
   },
   {
    "allow_edit": "System Manager",
    "doc_status": "0",
    "is_optional_state": 0,
    "message": null,
    "next_action_email_template": null,
    "parent": "Event Approval",
    "parentfield": "states",
    "parenttype": "Workflow",
    "state": "Authorisation Pending",
    "update_field": null,
    "update_value": null
   },
   {
    "allow_edit": "Managing Director",
    "doc_status": "0",
    "is_optional_state": 0,
    "message": null,
    "next_action_email_template": null,
    "parent": "Event Approval",
    "parentfield": "states",
    "parenttype": "Workflow",
    "state": "Approved",
    "update_field": null,
    "update_value": null
   }
  ],
  "transitions": [
   {
    "action": "Send For Authorisation",
    "allow_self_approval": 1,
    "allowed": "Employee",
    "condition": null,
    "next_state": "Authorisation Pending",
    "parent": "Event Approval",
    "parentfield": "transitions",
    "parenttype": "Workflow",
    "state": "Pending"
   },
   {
    "action": "Authorised",
    "allow_self_approval": 1,
    "allowed": "Managing Director",
    "condition": null,
    "next_state": "Approved",
    "parent": "Event Approval",
    "parentfield": "transitions",
    "parenttype": "Workflow",
    "state": "Authorisation Pending"
   }
  ],
  "workflow_name": "Event Approval",
  "workflow_state_field": "workflow_state"
 },
 {
  "docstatus": 0,
  "doctype": "Workflow",
  "document_type": "Training Event",
  "is_active": 1,
  "modified": "2021-02-16 17:31:55.436563",
  "name": "Training Approval",
  "override_status": 0,
  "parent": null,
  "parentfield": null,
  "parenttype": null,
  "send_email_alert": 1,
  "states": [
   {
    "allow_edit": "Employee",
    "doc_status": "0",
    "is_optional_state": 0,
    "message": null,
    "next_action_email_template": null,
    "parent": "Training Approval",
    "parentfield": "states",
    "parenttype": "Workflow",
    "state": "Pending",
    "update_field": null,
    "update_value": null
   },
   {
    "allow_edit": "System Manager",
    "doc_status": "0",
    "is_optional_state": 0,
    "message": null,
    "next_action_email_template": null,
    "parent": "Training Approval",
    "parentfield": "states",
    "parenttype": "Workflow",
    "state": "Authorisation Pending",
    "update_field": null,
    "update_value": null
   },
   {
    "allow_edit": "System Manager",
    "doc_status": "1",
    "is_optional_state": 0,
    "message": null,
    "next_action_email_template": null,
    "parent": "Training Approval",
    "parentfield": "states",
    "parenttype": "Workflow",
    "state": "Approved",
    "update_field": null,
    "update_value": null
   },
   {
    "allow_edit": "System Manager",
    "doc_status": "2",
    "is_optional_state": 0,
    "message": null,
    "next_action_email_template": null,
    "parent": "Training Approval",
    "parentfield": "states",
    "parenttype": "Workflow",
    "state": "Cancelled",
    "update_field": null,
    "update_value": null
   }
  ],
  "transitions": [
   {
    "action": "Send For Authorisation",
    "allow_self_approval": 1,
    "allowed": "Employee",
    "condition": null,
    "next_state": "Authorisation Pending",
    "parent": "Training Approval",
    "parentfield": "transitions",
    "parenttype": "Workflow",
    "state": "Pending"
   },
   {
    "action": "Authorised",
    "allow_self_approval": 1,
    "allowed": "System Manager",
    "condition": null,
    "next_state": "Approved",
    "parent": "Training Approval",
    "parentfield": "transitions",
    "parenttype": "Workflow",
    "state": "Authorisation Pending"
   },
   {
    "action": "Cancel",
    "allow_self_approval": 1,
    "allowed": "System Manager",
    "condition": null,
    "next_state": "Cancelled",
    "parent": "Training Approval",
    "parentfield": "transitions",
    "parenttype": "Workflow",
    "state": "Approved"
   }
  ],
  "workflow_name": "Training Approval",
  "workflow_state_field": "workflow_state"
 },
 {
  "docstatus": 0,
  "doctype": "Workflow",
  "document_type": "Quality Procedure",
  "is_active": 1,
  "modified": "2021-02-16 17:31:37.597927",
  "name": "Quality",
  "override_status": 0,
  "parent": null,
  "parentfield": null,
  "parenttype": null,
  "send_email_alert": 1,
  "states": [
   {
    "allow_edit": "Employee",
    "doc_status": "0",
    "is_optional_state": 0,
    "message": null,
    "next_action_email_template": null,
    "parent": "Quality",
    "parentfield": "states",
    "parenttype": "Workflow",
    "state": "Pending",
    "update_field": null,
    "update_value": null
   },
   {
    "allow_edit": "System Manager",
    "doc_status": "0",
    "is_optional_state": 0,
    "message": null,
    "next_action_email_template": null,
    "parent": "Quality",
    "parentfield": "states",
    "parenttype": "Workflow",
    "state": "Authorisation Pending",
    "update_field": null,
    "update_value": null
   },
   {
    "allow_edit": "System Manager",
    "doc_status": "0",
    "is_optional_state": 0,
    "message": null,
    "next_action_email_template": null,
    "parent": "Quality",
    "parentfield": "states",
    "parenttype": "Workflow",
    "state": "Approved",
    "update_field": null,
    "update_value": null
   },
   {
    "allow_edit": "System Manager",
    "doc_status": "0",
    "is_optional_state": 0,
    "message": null,
    "next_action_email_template": null,
    "parent": "Quality",
    "parentfield": "states",
    "parenttype": "Workflow",
    "state": "Cancelled",
    "update_field": null,
    "update_value": null
   }
  ],
  "transitions": [
   {
    "action": "Send For Authorisation",
    "allow_self_approval": 1,
    "allowed": "Employee",
    "condition": null,
    "next_state": "Authorisation Pending",
    "parent": "Quality",
    "parentfield": "transitions",
    "parenttype": "Workflow",
    "state": "Pending"
   },
   {
    "action": "Authorised",
    "allow_self_approval": 1,
    "allowed": "System Manager",
    "condition": null,
    "next_state": "Approved",
    "parent": "Quality",
    "parentfield": "transitions",
    "parenttype": "Workflow",
    "state": "Authorisation Pending"
   },
   {
    "action": "Cancel",
    "allow_self_approval": 1,
    "allowed": "System Manager",
    "condition": null,
    "next_state": "Cancelled",
    "parent": "Quality",
    "parentfield": "transitions",
    "parenttype": "Workflow",
    "state": "Approved"
   }
  ],
  "workflow_name": "Quality",
  "workflow_state_field": "workflow_state"
 },
 {
  "docstatus": 0,
  "doctype": "Workflow",
  "document_type": "BOM",
  "is_active": 0,
  "modified": "2021-02-26 10:35:35.289622",
  "name": "BOM Approval Mam",
  "override_status": 0,
  "parent": null,
  "parentfield": null,
  "parenttype": null,
  "send_email_alert": 0,
  "states": [
   {
    "allow_edit": "Manufacturing User",
    "doc_status": "0",
    "is_optional_state": 0,
    "message": null,
    "next_action_email_template": null,
    "parent": "BOM Approval Mam",
    "parentfield": "states",
    "parenttype": "Workflow",
    "state": "Draft",
    "update_field": null,
    "update_value": null
   },
   {
    "allow_edit": "Manufacturing User",
    "doc_status": "0",
    "is_optional_state": 0,
    "message": null,
    "next_action_email_template": null,
    "parent": "BOM Approval Mam",
    "parentfield": "states",
    "parenttype": "Workflow",
    "state": "Authorisation Pending",
    "update_field": null,
    "update_value": null
   },
   {
    "allow_edit": "Managing Director",
    "doc_status": "1",
    "is_optional_state": 0,
    "message": null,
    "next_action_email_template": null,
    "parent": "BOM Approval Mam",
    "parentfield": "states",
    "parenttype": "Workflow",
    "state": "Approved",
    "update_field": null,
    "update_value": null
   },
   {
    "allow_edit": "Managing Director",
    "doc_status": "2",
    "is_optional_state": 0,
    "message": null,
    "next_action_email_template": null,
    "parent": "BOM Approval Mam",
    "parentfield": "states",
    "parenttype": "Workflow",
    "state": "Rejected",
    "update_field": null,
    "update_value": null
   }
  ],
  "transitions": [
   {
    "action": "Send For Authorisation",
    "allow_self_approval": 1,
    "allowed": "Manufacturing User",
    "condition": null,
    "next_state": "Authorisation Pending",
    "parent": "BOM Approval Mam",
    "parentfield": "transitions",
    "parenttype": "Workflow",
    "state": "Draft"
   },
   {
    "action": "Authorise",
    "allow_self_approval": 1,
    "allowed": "Managing Director",
    "condition": null,
    "next_state": "Approved",
    "parent": "BOM Approval Mam",
    "parentfield": "transitions",
    "parenttype": "Workflow",
    "state": "Authorisation Pending"
   },
   {
    "action": "Reject",
    "allow_self_approval": 1,
    "allowed": "Managing Director",
    "condition": null,
    "next_state": "Rejected",
    "parent": "BOM Approval Mam",
    "parentfield": "transitions",
    "parenttype": "Workflow",
    "state": "Approved"
   }
  ],
  "workflow_name": "BOM Approval Mam",
  "workflow_state_field": "workflow_state"
 },
 {
  "docstatus": 0,
  "doctype": "Workflow",
  "document_type": "Delivery Note",
  "is_active": 1,
  "modified": "2021-03-18 11:31:27.345319",
  "name": "DN Approval",
  "override_status": 0,
  "parent": null,
  "parentfield": null,
  "parenttype": null,
  "send_email_alert": 1,
  "states": [
   {
    "allow_edit": "Sales User",
    "doc_status": "0",
    "is_optional_state": 0,
    "message": null,
    "next_action_email_template": null,
    "parent": "DN Approval",
    "parentfield": "states",
    "parenttype": "Workflow",
    "state": "Draft",
    "update_field": null,
    "update_value": null
   },
   {
    "allow_edit": "Sales Manager",
    "doc_status": "0",
    "is_optional_state": 0,
    "message": null,
    "next_action_email_template": null,
    "parent": "DN Approval",
    "parentfield": "states",
    "parenttype": "Workflow",
    "state": "Pending",
    "update_field": null,
    "update_value": null
   },
   {
    "allow_edit": "Sales Manager",
    "doc_status": "1",
    "is_optional_state": 0,
    "message": null,
    "next_action_email_template": null,
    "parent": "DN Approval",
    "parentfield": "states",
    "parenttype": "Workflow",
    "state": "To Bill on Approval",
    "update_field": null,
    "update_value": null
   },
   {
    "allow_edit": "Sales Manager",
    "doc_status": "1",
    "is_optional_state": 0,
    "message": null,
    "next_action_email_template": null,
    "parent": "DN Approval",
    "parentfield": "states",
    "parenttype": "Workflow",
    "state": "Approved",
    "update_field": null,
    "update_value": null
   },
   {
    "allow_edit": "Sales Manager",
    "doc_status": "2",
    "is_optional_state": 0,
    "message": null,
    "next_action_email_template": null,
    "parent": "DN Approval",
    "parentfield": "states",
    "parenttype": "Workflow",
    "state": "Cancelled",
    "update_field": null,
    "update_value": null
   }
  ],
  "transitions": [
   {
    "action": "Send For Authorisation",
    "allow_self_approval": 1,
    "allowed": "Sales User",
    "condition": null,
    "next_state": "Pending",
    "parent": "DN Approval",
    "parentfield": "transitions",
    "parenttype": "Workflow",
    "state": "Draft"
   },
   {
    "action": "Approve Without Payment",
    "allow_self_approval": 1,
    "allowed": "Sales Manager",
    "condition": "doc.outstanding_amount > 0",
    "next_state": "To Bill on Approval",
    "parent": "DN Approval",
    "parentfield": "transitions",
    "parenttype": "Workflow",
    "state": "Pending"
   },
   {
    "action": "Approve",
    "allow_self_approval": 1,
    "allowed": "Sales Manager",
    "condition": "doc.outstanding_amount == 0",
    "next_state": "Approved",
    "parent": "DN Approval",
    "parentfield": "transitions",
    "parenttype": "Workflow",
    "state": "Pending"
   },
   {
    "action": "Cancel",
    "allow_self_approval": 1,
    "allowed": "Sales Manager",
    "condition": "",
    "next_state": "Cancelled",
    "parent": "DN Approval",
    "parentfield": "transitions",
    "parenttype": "Workflow",
    "state": "To Bill on Approval"
   },
   {
    "action": "Cancel",
    "allow_self_approval": 1,
    "allowed": "Sales Manager",
    "condition": "",
    "next_state": "Cancelled",
    "parent": "DN Approval",
    "parentfield": "transitions",
    "parenttype": "Workflow",
    "state": "Approved"
   }
  ],
  "workflow_name": "DN Approval",
  "workflow_state_field": "workflow_state"
 },
 {
  "docstatus": 0,
  "doctype": "Workflow",
  "document_type": "Material Request",
  "is_active": 1,
  "modified": "2021-03-24 17:30:40.534492",
  "name": "MR Approval",
  "override_status": 0,
  "parent": null,
  "parentfield": null,
  "parenttype": null,
  "send_email_alert": 1,
  "states": [
   {
    "allow_edit": "Purchase User",
    "doc_status": "0",
    "is_optional_state": 0,
    "message": null,
    "next_action_email_template": null,
    "parent": "MR Approval",
    "parentfield": "states",
    "parenttype": "Workflow",
    "state": "Draft",
    "update_field": null,
    "update_value": null
   },
   {
    "allow_edit": "Purchase Manager",
    "doc_status": "0",
    "is_optional_state": 0,
    "message": null,
    "next_action_email_template": null,
    "parent": "MR Approval",
    "parentfield": "states",
    "parenttype": "Workflow",
    "state": "Pending",
    "update_field": null,
    "update_value": null
   },
   {
    "allow_edit": "Purchase User",
    "doc_status": "0",
    "is_optional_state": 0,
    "message": null,
    "next_action_email_template": null,
    "parent": "MR Approval",
    "parentfield": "states",
    "parenttype": "Workflow",
    "state": "Pending",
    "update_field": null,
    "update_value": null
   },
   {
    "allow_edit": "Purchase Manager",
    "doc_status": "1",
    "is_optional_state": 0,
    "message": null,
    "next_action_email_template": null,
    "parent": "MR Approval",
    "parentfield": "states",
    "parenttype": "Workflow",
    "state": "Approved",
    "update_field": null,
    "update_value": null
   },
   {
    "allow_edit": "Projects Manager",
    "doc_status": "1",
    "is_optional_state": 0,
    "message": null,
    "next_action_email_template": null,
    "parent": "MR Approval",
    "parentfield": "states",
    "parenttype": "Workflow",
    "state": "Approved",
    "update_field": null,
    "update_value": null
   },
   {
    "allow_edit": "Purchase Manager",
    "doc_status": "2",
    "is_optional_state": 0,
    "message": null,
    "next_action_email_template": null,
    "parent": "MR Approval",
    "parentfield": "states",
    "parenttype": "Workflow",
    "state": "Cancelled",
    "update_field": null,
    "update_value": null
   },
   {
    "allow_edit": "Projects Manager",
    "doc_status": "2",
    "is_optional_state": 0,
    "message": null,
    "next_action_email_template": null,
    "parent": "MR Approval",
    "parentfield": "states",
    "parenttype": "Workflow",
    "state": "Cancelled",
    "update_field": null,
    "update_value": null
   },
   {
    "allow_edit": "Purchase User",
    "doc_status": "2",
    "is_optional_state": 0,
    "message": null,
    "next_action_email_template": null,
    "parent": "MR Approval",
    "parentfield": "states",
    "parenttype": "Workflow",
    "state": "Cancelled",
    "update_field": null,
    "update_value": null
   }
  ],
  "transitions": [
   {
    "action": "Send For Authorisation",
    "allow_self_approval": 1,
    "allowed": "Purchase User",
    "condition": null,
    "next_state": "Pending",
    "parent": "MR Approval",
    "parentfield": "transitions",
    "parenttype": "Workflow",
    "state": "Draft"
   },
   {
    "action": "Approve",
    "allow_self_approval": 1,
    "allowed": "Purchase Manager",
    "condition": null,
    "next_state": "Approved",
    "parent": "MR Approval",
    "parentfield": "transitions",
    "parenttype": "Workflow",
    "state": "Pending"
   },
   {
    "action": "Approve",
    "allow_self_approval": 1,
    "allowed": "Projects Manager",
    "condition": null,
    "next_state": "Approved",
    "parent": "MR Approval",
    "parentfield": "transitions",
    "parenttype": "Workflow",
    "state": "Pending"
   },
   {
    "action": "Approve",
    "allow_self_approval": 1,
    "allowed": "Purchase User",
    "condition": "doc.material_request_type==\"Manufacture\"",
    "next_state": "Approved",
    "parent": "MR Approval",
    "parentfield": "transitions",
    "parenttype": "Workflow",
    "state": "Pending"
   },
   {
    "action": "Approve",
    "allow_self_approval": 1,
    "allowed": "Managing Director",
    "condition": "doc.material_request_type!=\"Manufacture\"",
    "next_state": "Approved",
    "parent": "MR Approval",
    "parentfield": "transitions",
    "parenttype": "Workflow",
    "state": "Pending"
   },
   {
    "action": "Cancel",
    "allow_self_approval": 1,
    "allowed": "Purchase Manager",
    "condition": null,
    "next_state": "Cancelled",
    "parent": "MR Approval",
    "parentfield": "transitions",
    "parenttype": "Workflow",
    "state": "Approved"
   },
   {
    "action": "Cancel",
    "allow_self_approval": 1,
    "allowed": "Projects Manager",
    "condition": null,
    "next_state": "Cancelled",
    "parent": "MR Approval",
    "parentfield": "transitions",
    "parenttype": "Workflow",
    "state": "Approved"
   },
   {
    "action": "Cancel",
    "allow_self_approval": 1,
    "allowed": "Purchase User",
    "condition": null,
    "next_state": "Cancelled",
    "parent": "MR Approval",
    "parentfield": "transitions",
    "parenttype": "Workflow",
    "state": "Approved"
   }
  ],
  "workflow_name": "MR Approval",
  "workflow_state_field": "workflow_state"
 },
 {
  "docstatus": 0,
  "doctype": "Workflow",
  "document_type": "Production Plan",
  "is_active": 1,
  "modified": "2021-03-20 16:20:23.551670",
  "name": "Production Plan",
  "override_status": 1,
  "parent": null,
  "parentfield": null,
  "parenttype": null,
  "send_email_alert": 1,
  "states": [
   {
    "allow_edit": "Manufacturing Manager",
    "doc_status": "0",
    "is_optional_state": 0,
    "message": null,
    "next_action_email_template": null,
    "parent": "Production Plan",
    "parentfield": "states",
    "parenttype": "Workflow",
    "state": "Draft",
    "update_field": null,
    "update_value": null
   },
   {
    "allow_edit": "Projects Manager",
    "doc_status": "0",
    "is_optional_state": 0,
    "message": null,
    "next_action_email_template": null,
    "parent": "Production Plan",
    "parentfield": "states",
    "parenttype": "Workflow",
    "state": "Draft",
    "update_field": null,
    "update_value": null
   },
   {
    "allow_edit": "Managing Director",
    "doc_status": "0",
    "is_optional_state": 0,
    "message": null,
    "next_action_email_template": null,
    "parent": "Production Plan",
    "parentfield": "states",
    "parenttype": "Workflow",
    "state": "Authorisation Pending",
    "update_field": null,
    "update_value": null
   },
   {
    "allow_edit": "Projects Manager",
    "doc_status": "0",
    "is_optional_state": 0,
    "message": null,
    "next_action_email_template": null,
    "parent": "Production Plan",
    "parentfield": "states",
    "parenttype": "Workflow",
    "state": "Authorisation Pending",
    "update_field": null,
    "update_value": null
   },
   {
    "allow_edit": "Managing Director",
    "doc_status": "1",
    "is_optional_state": 0,
    "message": null,
    "next_action_email_template": null,
    "parent": "Production Plan",
    "parentfield": "states",
    "parenttype": "Workflow",
    "state": "Approved",
    "update_field": null,
    "update_value": null
   },
   {
    "allow_edit": "Projects Manager",
    "doc_status": "1",
    "is_optional_state": 0,
    "message": null,
    "next_action_email_template": null,
    "parent": "Production Plan",
    "parentfield": "states",
    "parenttype": "Workflow",
    "state": "Approved",
    "update_field": null,
    "update_value": null
   },
   {
    "allow_edit": "Managing Director",
    "doc_status": "2",
    "is_optional_state": 0,
    "message": null,
    "next_action_email_template": null,
    "parent": "Production Plan",
    "parentfield": "states",
    "parenttype": "Workflow",
    "state": "Cancelled",
    "update_field": null,
    "update_value": null
   }
  ],
  "transitions": [
   {
    "action": "Send For Authorisation",
    "allow_self_approval": 1,
    "allowed": "Manufacturing User",
    "condition": null,
    "next_state": "Authorisation Pending",
    "parent": "Production Plan",
    "parentfield": "transitions",
    "parenttype": "Workflow",
    "state": "Draft"
   },
   {
    "action": "Send For Authorisation",
    "allow_self_approval": 1,
    "allowed": "Projects Manager",
    "condition": null,
    "next_state": "Authorisation Pending",
    "parent": "Production Plan",
    "parentfield": "transitions",
    "parenttype": "Workflow",
    "state": "Draft"
   },
   {
    "action": "Approve",
    "allow_self_approval": 1,
    "allowed": "Projects Manager",
    "condition": null,
    "next_state": "Approved",
    "parent": "Production Plan",
    "parentfield": "transitions",
    "parenttype": "Workflow",
    "state": "Authorisation Pending"
   },
   {
    "action": "Approve",
    "allow_self_approval": 1,
    "allowed": "Managing Director",
    "condition": null,
    "next_state": "Approved",
    "parent": "Production Plan",
    "parentfield": "transitions",
    "parenttype": "Workflow",
    "state": "Authorisation Pending"
   },
   {
    "action": "Cancel",
    "allow_self_approval": 1,
    "allowed": "Managing Director",
    "condition": null,
    "next_state": "Cancelled",
    "parent": "Production Plan",
    "parentfield": "transitions",
    "parenttype": "Workflow",
    "state": "Approved"
   },
   {
    "action": "Cancel",
    "allow_self_approval": 1,
    "allowed": "Projects Manager",
    "condition": null,
    "next_state": "Cancelled",
    "parent": "Production Plan",
    "parentfield": "transitions",
    "parenttype": "Workflow",
    "state": "Approved"
   }
  ],
  "workflow_name": "Production Plan",
  "workflow_state_field": "workflow_state"
 },
 {
  "docstatus": 0,
  "doctype": "Workflow",
  "document_type": "Item",
  "is_active": 1,
  "modified": "2021-07-12 15:26:53.277463",
  "name": "Item Autorise",
  "override_status": 1,
  "parent": null,
  "parentfield": null,
  "parenttype": null,
  "send_email_alert": 0,
  "states": [
   {
    "allow_edit": "Item Manager",
    "doc_status": "0",
    "is_optional_state": 0,
    "message": null,
    "next_action_email_template": null,
    "parent": "Item Autorise",
    "parentfield": "states",
    "parenttype": "Workflow",
    "state": "Draft",
    "update_field": null,
    "update_value": null
   },
   {
    "allow_edit": "System Manager",
    "doc_status": "0",
    "is_optional_state": 0,
    "message": null,
    "next_action_email_template": null,
    "parent": "Item Autorise",
    "parentfield": "states",
    "parenttype": "Workflow",
    "state": "Authorisation Pending",
    "update_field": null,
    "update_value": null
   },
   {
    "allow_edit": "System Manager",
    "doc_status": "0",
    "is_optional_state": 0,
    "message": null,
    "next_action_email_template": null,
    "parent": "Item Autorise",
    "parentfield": "states",
    "parenttype": "Workflow",
    "state": "Approved",
    "update_field": null,
    "update_value": null
   },
   {
    "allow_edit": "Item Supervisor",
    "doc_status": "0",
    "is_optional_state": 0,
    "message": null,
    "next_action_email_template": null,
    "parent": "Item Autorise",
    "parentfield": "states",
    "parenttype": "Workflow",
    "state": "Rejected",
    "update_field": null,
    "update_value": null
   }
  ],
  "transitions": [
   {
    "action": "Send For Authorisation",
    "allow_self_approval": 1,
    "allowed": "Item Manager",
    "condition": "doc.item_group==\"Template\"",
    "next_state": "Authorisation Pending",
    "parent": "Item Autorise",
    "parentfield": "transitions",
    "parenttype": "Workflow",
    "state": "Draft"
   },
   {
    "action": "Approve",
    "allow_self_approval": 1,
    "allowed": "System Manager",
    "condition": "doc.item_group==\"Template\"",
    "next_state": "Approved",
    "parent": "Item Autorise",
    "parentfield": "transitions",
    "parenttype": "Workflow",
    "state": "Authorisation Pending"
   },
   {
    "action": "Reject",
    "allow_self_approval": 1,
    "allowed": "System Manager",
    "condition": "doc.item_group!=\"Template\"",
    "next_state": "Rejected",
    "parent": "Item Autorise",
    "parentfield": "transitions",
    "parenttype": "Workflow",
    "state": "Authorisation Pending"
   },
   {
    "action": "Reject",
    "allow_self_approval": 1,
    "allowed": "Item Supervisor",
    "condition": null,
    "next_state": "Rejected",
    "parent": "Item Autorise",
    "parentfield": "transitions",
    "parenttype": "Workflow",
    "state": "Authorisation Pending"
   }
  ],
  "workflow_name": "Item Autorise",
  "workflow_state_field": "workflow_state"
 },
 {
  "docstatus": 0,
  "doctype": "Workflow",
  "document_type": "Salary Slip",
  "is_active": 1,
  "modified": "2021-05-17 11:36:07.792688",
  "name": "Salary Slip",
  "override_status": 0,
  "parent": null,
  "parentfield": null,
  "parenttype": null,
  "send_email_alert": 1,
  "states": [
   {
    "allow_edit": "Employee",
    "doc_status": "0",
    "is_optional_state": 0,
    "message": null,
    "next_action_email_template": null,
    "parent": "Salary Slip",
    "parentfield": "states",
    "parenttype": "Workflow",
    "state": "Draft",
    "update_field": null,
    "update_value": null
   },
   {
    "allow_edit": "System Manager",
    "doc_status": "0",
    "is_optional_state": 0,
    "message": null,
    "next_action_email_template": null,
    "parent": "Salary Slip",
    "parentfield": "states",
    "parenttype": "Workflow",
    "state": "Draft",
    "update_field": null,
    "update_value": null
   },
   {
    "allow_edit": "HR Manager",
    "doc_status": "0",
    "is_optional_state": 0,
    "message": null,
    "next_action_email_template": null,
    "parent": "Salary Slip",
    "parentfield": "states",
    "parenttype": "Workflow",
    "state": "Pending",
    "update_field": null,
    "update_value": null
   },
   {
    "allow_edit": "HR Manager",
    "doc_status": "1",
    "is_optional_state": 0,
    "message": null,
    "next_action_email_template": null,
    "parent": "Salary Slip",
    "parentfield": "states",
    "parenttype": "Workflow",
    "state": "Approved",
    "update_field": null,
    "update_value": null
   },
   {
    "allow_edit": "HR Manager",
    "doc_status": "2",
    "is_optional_state": 0,
    "message": null,
    "next_action_email_template": null,
    "parent": "Salary Slip",
    "parentfield": "states",
    "parenttype": "Workflow",
    "state": "Cancelled",
    "update_field": null,
    "update_value": null
   }
  ],
  "transitions": [
   {
    "action": "Send For Authorisation",
    "allow_self_approval": 1,
    "allowed": "Employee",
    "condition": null,
    "next_state": "Pending",
    "parent": "Salary Slip",
    "parentfield": "transitions",
    "parenttype": "Workflow",
    "state": "Draft"
   },
   {
    "action": "Send For Authorisation",
    "allow_self_approval": 1,
    "allowed": "System Manager",
    "condition": null,
    "next_state": "Pending",
    "parent": "Salary Slip",
    "parentfield": "transitions",
    "parenttype": "Workflow",
    "state": "Draft"
   },
   {
    "action": "Approve",
    "allow_self_approval": 1,
    "allowed": "HR Manager",
    "condition": null,
    "next_state": "Approved",
    "parent": "Salary Slip",
    "parentfield": "transitions",
    "parenttype": "Workflow",
    "state": "Pending"
   },
   {
    "action": "Cancel",
    "allow_self_approval": 1,
    "allowed": "HR Manager",
    "condition": null,
    "next_state": "Cancelled",
    "parent": "Salary Slip",
    "parentfield": "transitions",
    "parenttype": "Workflow",
    "state": "Approved"
   }
  ],
  "workflow_name": "Salary Slip",
  "workflow_state_field": "workflow_state"
 },
 {
  "docstatus": 0,
  "doctype": "Workflow",
  "document_type": "BOM",
  "is_active": 1,
  "modified": "2021-04-02 13:54:13.487902",
  "name": "BOM Approval",
  "override_status": 0,
  "parent": "BOM",
  "parentfield": "__workflow_docs",
  "parenttype": "DocType",
  "send_email_alert": 0,
  "states": [
   {
    "allow_edit": "Manufacturing User",
    "doc_status": "0",
    "is_optional_state": 0,
    "message": null,
    "next_action_email_template": null,
    "parent": "BOM Approval",
    "parentfield": "states",
    "parenttype": "Workflow",
    "state": "Draft",
    "update_field": null,
    "update_value": null
   },
   {
    "allow_edit": "Manufacturing User",
    "doc_status": "0",
    "is_optional_state": 0,
    "message": null,
    "next_action_email_template": null,
    "parent": "BOM Approval",
    "parentfield": "states",
    "parenttype": "Workflow",
    "state": "Changes Pending",
    "update_field": null,
    "update_value": null
   },
   {
    "allow_edit": "Cutting Master",
    "doc_status": "0",
    "is_optional_state": 0,
    "message": null,
    "next_action_email_template": null,
    "parent": "BOM Approval",
    "parentfield": "states",
    "parenttype": "Workflow",
    "state": "Changes Pending",
    "update_field": null,
    "update_value": null
   },
   {
    "allow_edit": "Cutting Master",
    "doc_status": "0",
    "is_optional_state": 0,
    "message": null,
    "next_action_email_template": null,
    "parent": "BOM Approval",
    "parentfield": "states",
    "parenttype": "Workflow",
    "state": "Authorisation Pending",
    "update_field": null,
    "update_value": null
   },
   {
    "allow_edit": "Managing Director",
    "doc_status": "0",
    "is_optional_state": 0,
    "message": null,
    "next_action_email_template": null,
    "parent": "BOM Approval",
    "parentfield": "states",
    "parenttype": "Workflow",
    "state": "Authorisation Pending",
    "update_field": null,
    "update_value": null
   },
   {
    "allow_edit": "Managing Director",
    "doc_status": "0",
    "is_optional_state": 0,
    "message": null,
    "next_action_email_template": null,
    "parent": "BOM Approval",
    "parentfield": "states",
    "parenttype": "Workflow",
    "state": "Authorisation Pending",
    "update_field": null,
    "update_value": null
   },
   {
    "allow_edit": "Managing Director",
    "doc_status": "0",
    "is_optional_state": 0,
    "message": null,
    "next_action_email_template": null,
    "parent": "BOM Approval",
    "parentfield": "states",
    "parenttype": "Workflow",
    "state": "Acknowledged by Master",
    "update_field": null,
    "update_value": null
   },
   {
    "allow_edit": "Managing Director",
    "doc_status": "0",
    "is_optional_state": 0,
    "message": null,
    "next_action_email_template": null,
    "parent": "BOM Approval",
    "parentfield": "states",
    "parenttype": "Workflow",
    "state": "Acknowledge by Master",
    "update_field": null,
    "update_value": null
   },
   {
    "allow_edit": "Managing Director",
    "doc_status": "1",
    "is_optional_state": 0,
    "message": null,
    "next_action_email_template": null,
    "parent": "BOM Approval",
    "parentfield": "states",
    "parenttype": "Workflow",
    "state": "Approved",
    "update_field": null,
    "update_value": null
   },
   {
    "allow_edit": "Managing Director",
    "doc_status": "2",
    "is_optional_state": 0,
    "message": null,
    "next_action_email_template": null,
    "parent": "BOM Approval",
    "parentfield": "states",
    "parenttype": "Workflow",
    "state": "Rejected",
    "update_field": null,
    "update_value": null
   }
  ],
  "transitions": [
   {
    "action": "Send For Authorisation",
    "allow_self_approval": 1,
    "allowed": "Manufacturing User",
    "condition": null,
    "next_state": "Authorisation Pending",
    "parent": "BOM Approval",
    "parentfield": "transitions",
    "parenttype": "Workflow",
    "state": "Draft"
   },
   {
    "action": "Acknowledge",
    "allow_self_approval": 1,
    "allowed": "Cutting Master",
    "condition": null,
    "next_state": "Acknowledged by Master",
    "parent": "BOM Approval",
    "parentfield": "transitions",
    "parenttype": "Workflow",
    "state": "Authorisation Pending"
   },
   {
    "action": "Acknowledge",
    "allow_self_approval": 1,
    "allowed": "Managing Director",
    "condition": null,
    "next_state": "Acknowledged by Master",
    "parent": "BOM Approval",
    "parentfield": "transitions",
    "parenttype": "Workflow",
    "state": "Authorisation Pending"
   },
   {
    "action": "Need Changes",
    "allow_self_approval": 1,
    "allowed": "Cutting Master",
    "condition": null,
    "next_state": "Changes Pending",
    "parent": "BOM Approval",
    "parentfield": "transitions",
    "parenttype": "Workflow",
    "state": "Authorisation Pending"
   },
   {
    "action": "Need Changes",
    "allow_self_approval": 1,
    "allowed": "Managing Director",
    "condition": null,
    "next_state": "Changes Pending",
    "parent": "BOM Approval",
    "parentfield": "transitions",
    "parenttype": "Workflow",
    "state": "Authorisation Pending"
   },
   {
    "action": "Send For Authorisation",
    "allow_self_approval": 1,
    "allowed": "Manufacturing User",
    "condition": null,
    "next_state": "Authorisation Pending",
    "parent": "BOM Approval",
    "parentfield": "transitions",
    "parenttype": "Workflow",
    "state": "Changes Pending"
   },
   {
    "action": "Authorise",
    "allow_self_approval": 1,
    "allowed": "Managing Director",
    "condition": null,
    "next_state": "Approved",
    "parent": "BOM Approval",
    "parentfield": "transitions",
    "parenttype": "Workflow",
    "state": "Acknowledged by Master"
   },
   {
    "action": "Need Changes",
    "allow_self_approval": 1,
    "allowed": "Managing Director",
    "condition": null,
    "next_state": "Changes Pending",
    "parent": "BOM Approval",
    "parentfield": "transitions",
    "parenttype": "Workflow",
    "state": "Acknowledge by Master"
   },
   {
    "action": "Need Changes",
    "allow_self_approval": 1,
    "allowed": "Managing Director",
    "condition": null,
    "next_state": "Changes Pending",
    "parent": "BOM Approval",
    "parentfield": "transitions",
    "parenttype": "Workflow",
    "state": "Acknowledged by Master"
   },
   {
    "action": "Approve",
    "allow_self_approval": 1,
    "allowed": "Managing Director",
    "condition": null,
    "next_state": "Approved",
    "parent": "BOM Approval",
    "parentfield": "transitions",
    "parenttype": "Workflow",
    "state": "Acknowledge by Master"
   },
   {
    "action": "Reject",
    "allow_self_approval": 1,
    "allowed": "Managing Director",
    "condition": null,
    "next_state": "Rejected",
    "parent": "BOM Approval",
    "parentfield": "transitions",
    "parenttype": "Workflow",
    "state": "Approved"
   }
  ],
  "workflow_name": "BOM Approval",
  "workflow_state_field": "workflow_state"
 },
 {
  "docstatus": 0,
  "doctype": "Workflow",
  "document_type": "Drawing",
  "is_active": 1,
  "modified": "2021-07-29 14:07:58.159013",
  "name": "Drawing Workflow",
  "override_status": 0,
  "parent": null,
  "parentfield": null,
  "parenttype": null,
  "send_email_alert": 0,
  "states": [
   {
    "allow_edit": "Projects User",
    "doc_status": "0",
    "is_optional_state": 0,
    "message": null,
    "next_action_email_template": null,
    "parent": "Drawing Workflow",
    "parentfield": "states",
    "parenttype": "Workflow",
    "state": "Draft",
    "update_field": null,
    "update_value": null
   },
   {
    "allow_edit": "Projects User",
    "doc_status": "0",
    "is_optional_state": 0,
    "message": null,
    "next_action_email_template": null,
    "parent": "Drawing Workflow",
    "parentfield": "states",
    "parenttype": "Workflow",
    "state": "Changes Pending",
    "update_field": null,
    "update_value": null
   },
   {
    "allow_edit": "Managing Director",
    "doc_status": "0",
    "is_optional_state": 0,
    "message": null,
    "next_action_email_template": null,
    "parent": "Drawing Workflow",
    "parentfield": "states",
    "parenttype": "Workflow",
    "state": "Authorisation Pending",
    "update_field": null,
    "update_value": null
   },
   {
    "allow_edit": "Managing Director",
    "doc_status": "0",
    "is_optional_state": 0,
    "message": null,
    "next_action_email_template": null,
    "parent": "Drawing Workflow",
    "parentfield": "states",
    "parenttype": "Workflow",
    "state": "Authorisation Pending",
    "update_field": null,
    "update_value": null
   },
   {
    "allow_edit": "Managing Director",
    "doc_status": "0",
    "is_optional_state": 0,
    "message": null,
    "next_action_email_template": null,
    "parent": "Drawing Workflow",
    "parentfield": "states",
    "parenttype": "Workflow",
    "state": "Acknowledged by Master",
    "update_field": null,
    "update_value": null
   },
   {
    "allow_edit": "Managing Director",
    "doc_status": "0",
    "is_optional_state": 0,
    "message": null,
    "next_action_email_template": null,
    "parent": "Drawing Workflow",
    "parentfield": "states",
    "parenttype": "Workflow",
    "state": "Acknowledge by Master",
    "update_field": null,
    "update_value": null
   },
   {
    "allow_edit": "Managing Director",
    "doc_status": "1",
    "is_optional_state": 0,
    "message": null,
    "next_action_email_template": null,
    "parent": "Drawing Workflow",
    "parentfield": "states",
    "parenttype": "Workflow",
    "state": "Approved",
    "update_field": null,
    "update_value": null
   },
   {
    "allow_edit": "Managing Director",
    "doc_status": "0",
    "is_optional_state": 0,
    "message": null,
    "next_action_email_template": null,
    "parent": "Drawing Workflow",
    "parentfield": "states",
    "parenttype": "Workflow",
    "state": "Rejected",
    "update_field": null,
    "update_value": null
   },
   {
    "allow_edit": "Managing Director",
    "doc_status": "2",
    "is_optional_state": 0,
    "message": null,
    "next_action_email_template": null,
    "parent": "Drawing Workflow",
    "parentfield": "states",
    "parenttype": "Workflow",
    "state": "Cancelled",
    "update_field": null,
    "update_value": null
   }
  ],
  "transitions": [
   {
    "action": "Send For Authorisation",
    "allow_self_approval": 1,
    "allowed": "Projects User",
    "condition": null,
    "next_state": "Authorisation Pending",
    "parent": "Drawing Workflow",
    "parentfield": "transitions",
    "parenttype": "Workflow",
    "state": "Draft"
   },
   {
    "action": "Acknowledge",
    "allow_self_approval": 1,
    "allowed": "Managing Director",
    "condition": null,
    "next_state": "Acknowledged by Master",
    "parent": "Drawing Workflow",
    "parentfield": "transitions",
    "parenttype": "Workflow",
    "state": "Authorisation Pending"
   },
   {
    "action": "Need Changes",
    "allow_self_approval": 1,
    "allowed": "Projects User",
    "condition": null,
    "next_state": "Changes Pending",
    "parent": "Drawing Workflow",
    "parentfield": "transitions",
    "parenttype": "Workflow",
    "state": "Authorisation Pending"
   },
   {
    "action": "Send For Authorisation",
    "allow_self_approval": 1,
    "allowed": "Projects User",
    "condition": null,
    "next_state": "Authorisation Pending",
    "parent": "Drawing Workflow",
    "parentfield": "transitions",
    "parenttype": "Workflow",
    "state": "Changes Pending"
   },
   {
    "action": "Authorise",
    "allow_self_approval": 1,
    "allowed": "Managing Director",
    "condition": null,
    "next_state": "Approved",
    "parent": "Drawing Workflow",
    "parentfield": "transitions",
    "parenttype": "Workflow",
    "state": "Acknowledged by Master"
   },
   {
    "action": "Reject",
    "allow_self_approval": 1,
    "allowed": "Managing Director",
    "condition": null,
    "next_state": "Rejected",
    "parent": "Drawing Workflow",
    "parentfield": "transitions",
    "parenttype": "Workflow",
    "state": "Acknowledged by Master"
   },
   {
    "action": "Need Changes",
    "allow_self_approval": 1,
    "allowed": "Managing Director",
    "condition": null,
    "next_state": "Changes Pending",
    "parent": "Drawing Workflow",
    "parentfield": "transitions",
    "parenttype": "Workflow",
    "state": "Acknowledge by Master"
   },
   {
    "action": "Need Changes",
    "allow_self_approval": 1,
    "allowed": "Managing Director",
    "condition": null,
    "next_state": "Changes Pending",
    "parent": "Drawing Workflow",
    "parentfield": "transitions",
    "parenttype": "Workflow",
    "state": "Acknowledged by Master"
   },
   {
    "action": "Approve",
    "allow_self_approval": 1,
    "allowed": "Managing Director",
    "condition": null,
    "next_state": "Approved",
    "parent": "Drawing Workflow",
    "parentfield": "transitions",
    "parenttype": "Workflow",
    "state": "Acknowledge by Master"
   },
   {
    "action": "Reject",
    "allow_self_approval": 1,
    "allowed": "Managing Director",
    "condition": null,
    "next_state": "Rejected",
    "parent": "Drawing Workflow",
    "parentfield": "transitions",
    "parenttype": "Workflow",
    "state": "Acknowledge by Master"
   },
   {
    "action": "Cancel",
    "allow_self_approval": 1,
    "allowed": "Managing Director",
    "condition": null,
    "next_state": "Cancelled",
    "parent": "Drawing Workflow",
    "parentfield": "transitions",
    "parenttype": "Workflow",
    "state": "Approved"
   },
   {
    "action": "Send For Authorisation",
    "allow_self_approval": 1,
    "allowed": "Projects User",
    "condition": null,
    "next_state": "Authorisation Pending",
    "parent": "Drawing Workflow",
    "parentfield": "transitions",
    "parenttype": "Workflow",
    "state": "Rejected"
   }
  ],
  "workflow_name": "Drawing Workflow",
  "workflow_state_field": "workflow_state"
 },
 {
  "docstatus": 0,
  "doctype": "Workflow",
  "document_type": "Sample",
  "is_active": 1,
  "modified": "2021-07-29 14:07:25.619073",
  "name": "Sample Workflow",
  "override_status": 0,
  "parent": null,
  "parentfield": null,
  "parenttype": null,
  "send_email_alert": 0,
  "states": [
   {
    "allow_edit": "Projects User",
    "doc_status": "0",
    "is_optional_state": 0,
    "message": null,
    "next_action_email_template": null,
    "parent": "Sample Workflow",
    "parentfield": "states",
    "parenttype": "Workflow",
    "state": "Draft",
    "update_field": null,
    "update_value": null
   },
   {
    "allow_edit": "Projects User",
    "doc_status": "0",
    "is_optional_state": 0,
    "message": null,
    "next_action_email_template": null,
    "parent": "Sample Workflow",
    "parentfield": "states",
    "parenttype": "Workflow",
    "state": "Changes Pending",
    "update_field": null,
    "update_value": null
   },
   {
    "allow_edit": "Managing Director",
    "doc_status": "0",
    "is_optional_state": 0,
    "message": null,
    "next_action_email_template": null,
    "parent": "Sample Workflow",
    "parentfield": "states",
    "parenttype": "Workflow",
    "state": "Authorisation Pending",
    "update_field": null,
    "update_value": null
   },
   {
    "allow_edit": "Managing Director",
    "doc_status": "0",
    "is_optional_state": 0,
    "message": null,
    "next_action_email_template": null,
    "parent": "Sample Workflow",
    "parentfield": "states",
    "parenttype": "Workflow",
    "state": "Authorisation Pending",
    "update_field": null,
    "update_value": null
   },
   {
    "allow_edit": "Managing Director",
    "doc_status": "0",
    "is_optional_state": 0,
    "message": null,
    "next_action_email_template": null,
    "parent": "Sample Workflow",
    "parentfield": "states",
    "parenttype": "Workflow",
    "state": "Acknowledged by Subcontradictor",
    "update_field": null,
    "update_value": null
   },
   {
    "allow_edit": "Managing Director",
    "doc_status": "1",
    "is_optional_state": 0,
    "message": null,
    "next_action_email_template": null,
    "parent": "Sample Workflow",
    "parentfield": "states",
    "parenttype": "Workflow",
    "state": "Approved",
    "update_field": null,
    "update_value": null
   },
   {
    "allow_edit": "Managing Director",
    "doc_status": "0",
    "is_optional_state": 0,
    "message": null,
    "next_action_email_template": null,
    "parent": "Sample Workflow",
    "parentfield": "states",
    "parenttype": "Workflow",
    "state": "Rejected",
    "update_field": null,
    "update_value": null
   },
   {
    "allow_edit": "Managing Director",
    "doc_status": "2",
    "is_optional_state": 0,
    "message": null,
    "next_action_email_template": null,
    "parent": "Sample Workflow",
    "parentfield": "states",
    "parenttype": "Workflow",
    "state": "Cancelled",
    "update_field": null,
    "update_value": null
   }
  ],
  "transitions": [
   {
    "action": "Send For Authorisation",
    "allow_self_approval": 1,
    "allowed": "Projects User",
    "condition": null,
    "next_state": "Authorisation Pending",
    "parent": "Sample Workflow",
    "parentfield": "transitions",
    "parenttype": "Workflow",
    "state": "Draft"
   },
   {
    "action": "Acknowledge",
    "allow_self_approval": 1,
    "allowed": "Managing Director",
    "condition": null,
    "next_state": "Acknowledged by Subcontradictor",
    "parent": "Sample Workflow",
    "parentfield": "transitions",
    "parenttype": "Workflow",
    "state": "Authorisation Pending"
   },
   {
    "action": "Need Changes",
    "allow_self_approval": 1,
    "allowed": "Projects User",
    "condition": null,
    "next_state": "Changes Pending",
    "parent": "Sample Workflow",
    "parentfield": "transitions",
    "parenttype": "Workflow",
    "state": "Authorisation Pending"
   },
   {
    "action": "Send For Authorisation",
    "allow_self_approval": 1,
    "allowed": "Projects User",
    "condition": null,
    "next_state": "Authorisation Pending",
    "parent": "Sample Workflow",
    "parentfield": "transitions",
    "parenttype": "Workflow",
    "state": "Changes Pending"
   },
   {
    "action": "Approve",
    "allow_self_approval": 1,
    "allowed": "Managing Director",
    "condition": null,
    "next_state": "Approved",
    "parent": "Sample Workflow",
    "parentfield": "transitions",
    "parenttype": "Workflow",
    "state": "Acknowledged by Subcontradictor"
   },
   {
    "action": "Reject",
    "allow_self_approval": 1,
    "allowed": "Managing Director",
    "condition": null,
    "next_state": "Rejected",
    "parent": "Sample Workflow",
    "parentfield": "transitions",
    "parenttype": "Workflow",
    "state": "Acknowledged by Subcontradictor"
   },
   {
    "action": "Need Changes",
    "allow_self_approval": 1,
    "allowed": "Managing Director",
    "condition": null,
    "next_state": "Changes Pending",
    "parent": "Sample Workflow",
    "parentfield": "transitions",
    "parenttype": "Workflow",
    "state": "Acknowledged by Subcontradictor"
   },
   {
    "action": "Cancel",
    "allow_self_approval": 1,
    "allowed": "Managing Director",
    "condition": null,
    "next_state": "Cancelled",
    "parent": "Sample Workflow",
    "parentfield": "transitions",
    "parenttype": "Workflow",
    "state": "Approved"
   },
   {
    "action": "Send For Authorisation",
    "allow_self_approval": 1,
    "allowed": "Managing Director",
    "condition": null,
    "next_state": "Authorisation Pending",
    "parent": "Sample Workflow",
    "parentfield": "transitions",
    "parenttype": "Workflow",
    "state": "Rejected"
   }
  ],
  "workflow_name": "Sample Workflow",
  "workflow_state_field": "workflow_state"
 },
 {
  "docstatus": 0,
  "doctype": "Workflow",
  "document_type": "Asset Movement",
  "is_active": 1,
  "modified": "2021-07-08 14:49:33.361039",
  "name": "Asset Movement Workflow",
  "override_status": 0,
  "parent": null,
  "parentfield": null,
  "parenttype": null,
  "send_email_alert": 0,
  "states": [
   {
    "allow_edit": "Manufacturing User",
    "doc_status": "0",
    "is_optional_state": 0,
    "message": null,
    "next_action_email_template": null,
    "parent": "Asset Movement Workflow",
    "parentfield": "states",
    "parenttype": "Workflow",
    "state": "Draft",
    "update_field": null,
    "update_value": null
   },
   {
    "allow_edit": "Manufacturing Manager",
    "doc_status": "0",
    "is_optional_state": 0,
    "message": null,
    "next_action_email_template": null,
    "parent": "Asset Movement Workflow",
    "parentfield": "states",
    "parenttype": "Workflow",
    "state": "Draft",
    "update_field": null,
    "update_value": null
   },
   {
    "allow_edit": "Guard",
    "doc_status": "0",
    "is_optional_state": 0,
    "message": null,
    "next_action_email_template": null,
    "parent": "Asset Movement Workflow",
    "parentfield": "states",
    "parenttype": "Workflow",
    "state": "Authorisation Pending",
    "update_field": null,
    "update_value": null
   },
   {
    "allow_edit": "Projects Manager",
    "doc_status": "0",
    "is_optional_state": 0,
    "message": null,
    "next_action_email_template": null,
    "parent": "Asset Movement Workflow",
    "parentfield": "states",
    "parenttype": "Workflow",
    "state": "Authorisation Pending",
    "update_field": null,
    "update_value": null
   },
   {
    "allow_edit": "Manufacturing User",
    "doc_status": "0",
    "is_optional_state": 0,
    "message": null,
    "next_action_email_template": null,
    "parent": "Asset Movement Workflow",
    "parentfield": "states",
    "parenttype": "Workflow",
    "state": "Authorised",
    "update_field": null,
    "update_value": null
   },
   {
    "allow_edit": "Manufacturing User",
    "doc_status": "1",
    "is_optional_state": 0,
    "message": null,
    "next_action_email_template": null,
    "parent": "Asset Movement Workflow",
    "parentfield": "states",
    "parenttype": "Workflow",
    "state": "Received",
    "update_field": null,
    "update_value": null
   },
   {
    "allow_edit": "Manufacturing Manager",
    "doc_status": "1",
    "is_optional_state": 0,
    "message": null,
    "next_action_email_template": null,
    "parent": "Asset Movement Workflow",
    "parentfield": "states",
    "parenttype": "Workflow",
    "state": "Approved",
    "update_field": null,
    "update_value": null
   },
   {
    "allow_edit": "Manufacturing Manager",
    "doc_status": "2",
    "is_optional_state": 0,
    "message": null,
    "next_action_email_template": null,
    "parent": "Asset Movement Workflow",
    "parentfield": "states",
    "parenttype": "Workflow",
    "state": "Rejected",
    "update_field": null,
    "update_value": null
   },
   {
    "allow_edit": "System Manager",
    "doc_status": "2",
    "is_optional_state": 0,
    "message": null,
    "next_action_email_template": null,
    "parent": "Asset Movement Workflow",
    "parentfield": "states",
    "parenttype": "Workflow",
    "state": "Rejected",
    "update_field": null,
    "update_value": null
   }
  ],
  "transitions": [
   {
    "action": "Send For Authorisation",
    "allow_self_approval": 1,
    "allowed": "Manufacturing User",
    "condition": "doc.purpose in (\"Issue\", \"Transfer\")",
    "next_state": "Authorisation Pending",
    "parent": "Asset Movement Workflow",
    "parentfield": "transitions",
    "parenttype": "Workflow",
    "state": "Draft"
   },
   {
    "action": "Authorise",
    "allow_self_approval": 1,
    "allowed": "Guard",
    "condition": "doc.purpose in (\"Issue\", \"Transfer\")",
    "next_state": "Authorised",
    "parent": "Asset Movement Workflow",
    "parentfield": "transitions",
    "parenttype": "Workflow",
    "state": "Authorisation Pending"
   },
   {
    "action": "Authorise",
    "allow_self_approval": 1,
    "allowed": "Projects Manager",
    "condition": "doc.purpose in (\"Issue\", \"Transfer\")",
    "next_state": "Authorised",
    "parent": "Asset Movement Workflow",
    "parentfield": "transitions",
    "parenttype": "Workflow",
    "state": "Authorisation Pending"
   },
   {
    "action": "Need Changes",
    "allow_self_approval": 1,
    "allowed": "Manufacturing Manager",
    "condition": "doc.purpose in (\"Issue\", \"Transfer\")",
    "next_state": "Draft",
    "parent": "Asset Movement Workflow",
    "parentfield": "transitions",
    "parenttype": "Workflow",
    "state": "Authorisation Pending"
   },
   {
    "action": "Receive",
    "allow_self_approval": 1,
    "allowed": "Manufacturing User",
    "condition": "doc.purpose in (\"Issue\", \"Transfer\")",
    "next_state": "Received",
    "parent": "Asset Movement Workflow",
    "parentfield": "transitions",
    "parenttype": "Workflow",
    "state": "Authorised"
   },
   {
    "action": "Receive",
    "allow_self_approval": 1,
    "allowed": "Head Cutting Master",
    "condition": "doc.purpose in (\"Issue\", \"Transfer\")",
    "next_state": "Received",
    "parent": "Asset Movement Workflow",
    "parentfield": "transitions",
    "parenttype": "Workflow",
    "state": "Authorised"
   },
   {
    "action": "Need Changes",
    "allow_self_approval": 1,
    "allowed": "Manufacturing Manager",
    "condition": "doc.purpose in (\"Issue\", \"Transfer\")",
    "next_state": "Draft",
    "parent": "Asset Movement Workflow",
    "parentfield": "transitions",
    "parenttype": "Workflow",
    "state": "Authorised"
   },
   {
    "action": "Reject",
    "allow_self_approval": 1,
    "allowed": "Manufacturing Manager",
    "condition": "doc.purpose in (\"Issue\", \"Transfer\")",
    "next_state": "Rejected",
    "parent": "Asset Movement Workflow",
    "parentfield": "transitions",
    "parenttype": "Workflow",
    "state": "Received"
   },
   {
    "action": "Reject",
    "allow_self_approval": 1,
    "allowed": "System Manager",
    "condition": "doc.purpose in (\"Issue\", \"Transfer\")",
    "next_state": "Rejected",
    "parent": "Asset Movement Workflow",
    "parentfield": "transitions",
    "parenttype": "Workflow",
    "state": "Received"
   },
   {
    "action": "Reject",
    "allow_self_approval": 1,
    "allowed": "Manufacturing Manager",
    "condition": "doc.purpose in (\"Issue\", \"Transfer\")",
    "next_state": "Rejected",
    "parent": "Asset Movement Workflow",
    "parentfield": "transitions",
    "parenttype": "Workflow",
    "state": "Approved"
   }
  ],
  "workflow_name": "Asset Movement Workflow",
  "workflow_state_field": "workflow_state"
 },
 {
  "docstatus": 0,
  "doctype": "Workflow",
  "document_type": "Pattern",
  "is_active": 1,
  "modified": "2021-07-29 19:30:07.680076",
  "name": "Pattern Workflow",
  "override_status": 0,
  "parent": null,
  "parentfield": null,
  "parenttype": null,
  "send_email_alert": 0,
  "states": [
   {
    "allow_edit": "Projects User",
    "doc_status": "0",
    "is_optional_state": 0,
    "message": null,
    "next_action_email_template": null,
    "parent": "Pattern Workflow",
    "parentfield": "states",
    "parenttype": "Workflow",
    "state": "Draft",
    "update_field": null,
    "update_value": null
   },
   {
    "allow_edit": "Projects User",
    "doc_status": "0",
    "is_optional_state": 0,
    "message": null,
    "next_action_email_template": null,
    "parent": "Pattern Workflow",
    "parentfield": "states",
    "parenttype": "Workflow",
    "state": "Changes Pending",
    "update_field": null,
    "update_value": null
   },
   {
    "allow_edit": "Cutting Master",
    "doc_status": "0",
    "is_optional_state": 0,
    "message": null,
    "next_action_email_template": null,
    "parent": "Pattern Workflow",
    "parentfield": "states",
    "parenttype": "Workflow",
    "state": "Authorisation Pending",
    "update_field": null,
    "update_value": null
   },
   {
    "allow_edit": "Projects User",
    "doc_status": "0",
    "is_optional_state": 0,
    "message": null,
    "next_action_email_template": null,
    "parent": "Pattern Workflow",
    "parentfield": "states",
    "parenttype": "Workflow",
    "state": "Authorisation Pending",
    "update_field": null,
    "update_value": null
   },
   {
    "allow_edit": "Cutting Master",
    "doc_status": "0",
    "is_optional_state": 0,
    "message": null,
    "next_action_email_template": null,
    "parent": "Pattern Workflow",
    "parentfield": "states",
    "parenttype": "Workflow",
    "state": "Acknowledged by Master",
    "update_field": null,
    "update_value": null
   },
   {
    "allow_edit": "Managing Director",
    "doc_status": "1",
    "is_optional_state": 0,
    "message": null,
    "next_action_email_template": null,
    "parent": "Pattern Workflow",
    "parentfield": "states",
    "parenttype": "Workflow",
    "state": "Approved",
    "update_field": null,
    "update_value": null
   },
   {
    "allow_edit": "Managing Director",
    "doc_status": "0",
    "is_optional_state": 0,
    "message": null,
    "next_action_email_template": null,
    "parent": "Pattern Workflow",
    "parentfield": "states",
    "parenttype": "Workflow",
    "state": "Rejected",
    "update_field": null,
    "update_value": null
   },
   {
    "allow_edit": "Managing Director",
    "doc_status": "2",
    "is_optional_state": 0,
    "message": null,
    "next_action_email_template": null,
    "parent": "Pattern Workflow",
    "parentfield": "states",
    "parenttype": "Workflow",
    "state": "Cancelled",
    "update_field": null,
    "update_value": null
   }
  ],
  "transitions": [
   {
    "action": "Send For Authorisation",
    "allow_self_approval": 1,
    "allowed": "Projects User",
    "condition": null,
    "next_state": "Authorisation Pending",
    "parent": "Pattern Workflow",
    "parentfield": "transitions",
    "parenttype": "Workflow",
    "state": "Draft"
   },
   {
    "action": "Need Changes",
    "allow_self_approval": 1,
    "allowed": "Projects User",
    "condition": null,
    "next_state": "Changes Pending",
    "parent": "Pattern Workflow",
    "parentfield": "transitions",
    "parenttype": "Workflow",
    "state": "Authorisation Pending"
   },
   {
    "action": "Send For Authorisation",
    "allow_self_approval": 1,
    "allowed": "Projects User",
    "condition": null,
    "next_state": "Authorisation Pending",
    "parent": "Pattern Workflow",
    "parentfield": "transitions",
    "parenttype": "Workflow",
    "state": "Changes Pending"
   },
   {
    "action": "Acknowledge",
    "allow_self_approval": 1,
    "allowed": "Cutting Master",
    "condition": null,
    "next_state": "Acknowledged by Master",
    "parent": "Pattern Workflow",
    "parentfield": "transitions",
    "parenttype": "Workflow",
    "state": "Authorisation Pending"
   },
   {
    "action": "Reject",
    "allow_self_approval": 1,
    "allowed": "Cutting Master",
    "condition": null,
    "next_state": "Rejected",
    "parent": "Pattern Workflow",
    "parentfield": "transitions",
    "parenttype": "Workflow",
    "state": "Acknowledged by Master"
   },
   {
    "action": "Need Changes",
    "allow_self_approval": 1,
    "allowed": "Cutting Master",
    "condition": null,
    "next_state": "Changes Pending",
    "parent": "Pattern Workflow",
    "parentfield": "transitions",
    "parenttype": "Workflow",
    "state": "Acknowledged by Master"
   },
   {
    "action": "Approve",
    "allow_self_approval": 1,
    "allowed": "Managing Director",
    "condition": null,
    "next_state": "Approved",
    "parent": "Pattern Workflow",
    "parentfield": "transitions",
    "parenttype": "Workflow",
    "state": "Acknowledged by Master"
   },
   {
    "action": "Cancel",
    "allow_self_approval": 1,
    "allowed": "Managing Director",
    "condition": null,
    "next_state": "Cancelled",
    "parent": "Pattern Workflow",
    "parentfield": "transitions",
    "parenttype": "Workflow",
    "state": "Approved"
   },
   {
    "action": "Send For Authorisation",
    "allow_self_approval": 1,
    "allowed": "Managing Director",
    "condition": null,
    "next_state": "Authorisation Pending",
    "parent": "Pattern Workflow",
    "parentfield": "transitions",
    "parenttype": "Workflow",
    "state": "Rejected"
   }
  ],
  "workflow_name": "Pattern Workflow",
  "workflow_state_field": "workflow_state"
 },
 {
  "docstatus": 0,
  "doctype": "Workflow",
  "document_type": "Purchase Order",
  "is_active": 1,
  "modified": "2021-11-29 09:53:29.323991",
  "name": "Purchase Order",
  "override_status": 0,
  "parent": null,
  "parentfield": null,
  "parenttype": null,
  "send_email_alert": 0,
  "states": [
   {
    "allow_edit": "All",
    "doc_status": "0",
    "is_optional_state": 0,
    "message": null,
    "next_action_email_template": null,
    "parent": "Purchase Order",
    "parentfield": "states",
    "parenttype": "Workflow",
    "state": "Draft",
    "update_field": null,
    "update_value": null
   },
   {
    "allow_edit": "All",
    "doc_status": "0",
    "is_optional_state": 0,
    "message": null,
    "next_action_email_template": null,
    "parent": "Purchase Order",
    "parentfield": "states",
    "parenttype": "Workflow",
    "state": "Authorisation Pending",
    "update_field": null,
    "update_value": null
   },
   {
    "allow_edit": "Projects Manager",
    "doc_status": "1",
    "is_optional_state": 0,
    "message": null,
    "next_action_email_template": null,
    "parent": "Purchase Order",
    "parentfield": "states",
    "parenttype": "Workflow",
    "state": "Approved",
    "update_field": null,
    "update_value": null
   },
   {
    "allow_edit": "Managing Director",
    "doc_status": "2",
    "is_optional_state": 0,
    "message": null,
    "next_action_email_template": null,
    "parent": "Purchase Order",
    "parentfield": "states",
    "parenttype": "Workflow",
    "state": "Rejected",
    "update_field": null,
    "update_value": null
   }
  ],
  "transitions": [
   {
    "action": "Send For Authorisation",
    "allow_self_approval": 1,
    "allowed": "All",
    "condition": null,
    "next_state": "Authorisation Pending",
    "parent": "Purchase Order",
    "parentfield": "transitions",
    "parenttype": "Workflow",
    "state": "Draft"
   },
   {
    "action": "Authorise",
    "allow_self_approval": 1,
    "allowed": "Sales Manager",
    "condition": null,
    "next_state": "Approved",
    "parent": "Purchase Order",
    "parentfield": "transitions",
    "parenttype": "Workflow",
    "state": "Authorisation Pending"
   },
   {
    "action": "Authorise",
    "allow_self_approval": 1,
    "allowed": "Projects Manager",
    "condition": null,
    "next_state": "Approved",
    "parent": "Purchase Order",
    "parentfield": "transitions",
    "parenttype": "Workflow",
    "state": "Authorisation Pending"
   },
   {
    "action": "Reject",
    "allow_self_approval": 1,
    "allowed": "Managing Director",
    "condition": null,
    "next_state": "Rejected",
    "parent": "Purchase Order",
    "parentfield": "transitions",
    "parenttype": "Workflow",
    "state": "Approved"
   }
  ],
  "workflow_name": "Purchase Order",
  "workflow_state_field": "workflow_state"
 },
 {
  "docstatus": 0,
  "doctype": "Workflow",
  "document_type": "Photo Shoot",
  "is_active": 1,
  "modified": "2021-11-25 16:07:20.389659",
  "name": "Photo Shoot",
  "override_status": 0,
  "parent": null,
  "parentfield": null,
  "parenttype": null,
  "send_email_alert": 0,
  "states": [
   {
    "allow_edit": "Projects User",
    "doc_status": "0",
    "is_optional_state": 0,
    "message": null,
    "next_action_email_template": null,
    "parent": "Photo Shoot",
    "parentfield": "states",
    "parenttype": "Workflow",
    "state": "Draft",
    "update_field": null,
    "update_value": null
   },
   {
    "allow_edit": "Projects User",
    "doc_status": "0",
    "is_optional_state": 0,
    "message": null,
    "next_action_email_template": null,
    "parent": "Photo Shoot",
    "parentfield": "states",
    "parenttype": "Workflow",
    "state": "Changes Pending",
    "update_field": null,
    "update_value": null
   },
   {
    "allow_edit": "Cutting Master",
    "doc_status": "0",
    "is_optional_state": 0,
    "message": null,
    "next_action_email_template": null,
    "parent": "Photo Shoot",
    "parentfield": "states",
    "parenttype": "Workflow",
    "state": "Authorisation Pending",
    "update_field": null,
    "update_value": null
   },
   {
    "allow_edit": "Projects User",
    "doc_status": "0",
    "is_optional_state": 0,
    "message": null,
    "next_action_email_template": null,
    "parent": "Photo Shoot",
    "parentfield": "states",
    "parenttype": "Workflow",
    "state": "Authorisation Pending",
    "update_field": null,
    "update_value": null
   },
   {
    "allow_edit": "Cutting Master",
    "doc_status": "0",
    "is_optional_state": 0,
    "message": null,
    "next_action_email_template": null,
    "parent": "Photo Shoot",
    "parentfield": "states",
    "parenttype": "Workflow",
    "state": "Acknowledged by Master",
    "update_field": null,
    "update_value": null
   },
   {
    "allow_edit": "Managing Director",
    "doc_status": "1",
    "is_optional_state": 0,
    "message": null,
    "next_action_email_template": null,
    "parent": "Photo Shoot",
    "parentfield": "states",
    "parenttype": "Workflow",
    "state": "Approved",
    "update_field": null,
    "update_value": null
   },
   {
    "allow_edit": "Managing Director",
    "doc_status": "0",
    "is_optional_state": 0,
    "message": null,
    "next_action_email_template": null,
    "parent": "Photo Shoot",
    "parentfield": "states",
    "parenttype": "Workflow",
    "state": "Rejected",
    "update_field": null,
    "update_value": null
   },
   {
    "allow_edit": "Managing Director",
    "doc_status": "2",
    "is_optional_state": 0,
    "message": null,
    "next_action_email_template": null,
    "parent": "Photo Shoot",
    "parentfield": "states",
    "parenttype": "Workflow",
    "state": "Cancelled",
    "update_field": null,
    "update_value": null
   }
  ],
  "transitions": [
   {
    "action": "Send For Authorisation",
    "allow_self_approval": 1,
    "allowed": "Projects User",
    "condition": null,
    "next_state": "Authorisation Pending",
    "parent": "Photo Shoot",
    "parentfield": "transitions",
    "parenttype": "Workflow",
    "state": "Draft"
   },
   {
    "action": "Need Changes",
    "allow_self_approval": 1,
    "allowed": "Projects User",
    "condition": null,
    "next_state": "Changes Pending",
    "parent": "Photo Shoot",
    "parentfield": "transitions",
    "parenttype": "Workflow",
    "state": "Authorisation Pending"
   },
   {
    "action": "Send For Authorisation",
    "allow_self_approval": 1,
    "allowed": "Projects User",
    "condition": null,
    "next_state": "Authorisation Pending",
    "parent": "Photo Shoot",
    "parentfield": "transitions",
    "parenttype": "Workflow",
    "state": "Changes Pending"
   },
   {
    "action": "Acknowledge",
    "allow_self_approval": 1,
    "allowed": "Cutting Master",
    "condition": null,
    "next_state": "Acknowledged by Master",
    "parent": "Photo Shoot",
    "parentfield": "transitions",
    "parenttype": "Workflow",
    "state": "Authorisation Pending"
   },
   {
    "action": "Reject",
    "allow_self_approval": 1,
    "allowed": "Cutting Master",
    "condition": null,
    "next_state": "Rejected",
    "parent": "Photo Shoot",
    "parentfield": "transitions",
    "parenttype": "Workflow",
    "state": "Acknowledged by Master"
   },
   {
    "action": "Need Changes",
    "allow_self_approval": 1,
    "allowed": "Cutting Master",
    "condition": null,
    "next_state": "Changes Pending",
    "parent": "Photo Shoot",
    "parentfield": "transitions",
    "parenttype": "Workflow",
    "state": "Acknowledged by Master"
   },
   {
    "action": "Approve",
    "allow_self_approval": 1,
    "allowed": "Managing Director",
    "condition": null,
    "next_state": "Approved",
    "parent": "Photo Shoot",
    "parentfield": "transitions",
    "parenttype": "Workflow",
    "state": "Acknowledged by Master"
   },
   {
    "action": "Cancel",
    "allow_self_approval": 1,
    "allowed": "Managing Director",
    "condition": null,
    "next_state": "Cancelled",
    "parent": "Photo Shoot",
    "parentfield": "transitions",
    "parenttype": "Workflow",
    "state": "Approved"
   },
   {
    "action": "Send For Authorisation",
    "allow_self_approval": 1,
    "allowed": "Managing Director",
    "condition": null,
    "next_state": "Authorisation Pending",
    "parent": "Photo Shoot",
    "parentfield": "transitions",
    "parenttype": "Workflow",
    "state": "Rejected"
   }
  ],
  "workflow_name": "Photo Shoot",
  "workflow_state_field": "workflow_state"
 },
 {
  "docstatus": 0,
  "doctype": "Workflow",
  "document_type": "Payment Entry",
  "is_active": 0,
  "modified": "2021-12-05 10:29:58.093996",
  "name": "Payment Entry",
  "override_status": 0,
  "parent": null,
  "parentfield": null,
  "parenttype": null,
  "send_email_alert": 1,
  "states": [
   {
    "allow_edit": "All",
    "doc_status": "0",
    "is_optional_state": 0,
    "message": null,
    "next_action_email_template": null,
    "parent": "Payment Entry",
    "parentfield": "states",
    "parenttype": "Workflow",
    "state": "Request to Internal Transfer",
    "update_field": null,
    "update_value": null
   },
   {
    "allow_edit": "Managing Director",
    "doc_status": "1",
    "is_optional_state": 0,
    "message": null,
    "next_action_email_template": null,
    "parent": "Payment Entry",
    "parentfield": "states",
    "parenttype": "Workflow",
    "state": "Authorised",
    "update_field": null,
    "update_value": null
   },
   {
    "allow_edit": "All",
    "doc_status": "1",
    "is_optional_state": 0,
    "message": null,
    "next_action_email_template": null,
    "parent": "Payment Entry",
    "parentfield": "states",
    "parenttype": "Workflow",
    "state": "Received",
    "update_field": null,
    "update_value": null
   },
   {
    "allow_edit": "Managing Director",
    "doc_status": "2",
    "is_optional_state": 0,
    "message": null,
    "next_action_email_template": null,
    "parent": "Payment Entry",
    "parentfield": "states",
    "parenttype": "Workflow",
    "state": "Cancelled",
    "update_field": null,
    "update_value": null
   },
   {
    "allow_edit": "All",
    "doc_status": "0",
    "is_optional_state": 0,
    "message": null,
    "next_action_email_template": null,
    "parent": "Payment Entry",
    "parentfield": "states",
    "parenttype": "Workflow",
    "state": "Draft",
    "update_field": null,
    "update_value": null
   },
   {
    "allow_edit": "All",
    "doc_status": "0",
    "is_optional_state": 0,
    "message": null,
    "next_action_email_template": null,
    "parent": "Payment Entry",
    "parentfield": "states",
    "parenttype": "Workflow",
    "state": "Authorisation Pending",
    "update_field": null,
    "update_value": null
   },
   {
    "allow_edit": "Managing Director",
    "doc_status": "2",
    "is_optional_state": 0,
    "message": null,
    "next_action_email_template": null,
    "parent": "Payment Entry",
    "parentfield": "states",
    "parenttype": "Workflow",
    "state": "Rejected",
    "update_field": null,
    "update_value": null
   }
  ],
  "transitions": [
   {
    "action": "Request to Internal Transfer",
    "allow_self_approval": 1,
    "allowed": "All",
    "condition": "doc.payment_transfer==\"Bank to Cash\"",
    "next_state": "Authorisation Pending",
    "parent": "Payment Entry",
    "parentfield": "transitions",
    "parenttype": "Workflow",
    "state": "Draft"
   },
   {
    "action": "Authorise",
    "allow_self_approval": 1,
    "allowed": "Managing Director",
    "condition": "doc.payment_transfer==\"Bank to Cash\"",
    "next_state": "Authorised",
    "parent": "Payment Entry",
    "parentfield": "transitions",
    "parenttype": "Workflow",
    "state": "Authorisation Pending"
   },
   {
    "action": "Receive",
    "allow_self_approval": 1,
    "allowed": "All",
    "condition": "doc.payment_transfer==\"Bank to Cash\"",
    "next_state": "Received",
    "parent": "Payment Entry",
    "parentfield": "transitions",
    "parenttype": "Workflow",
    "state": "Authorised"
   },
   {
    "action": "Reject",
    "allow_self_approval": 1,
    "allowed": "Managing Director",
    "condition": "doc.payment_transfer==\"Bank to Cash\"",
    "next_state": "Rejected",
    "parent": "Payment Entry",
    "parentfield": "transitions",
    "parenttype": "Workflow",
    "state": "Received"
   }
  ],
  "workflow_name": "Payment Entry",
  "workflow_state_field": "workflow_state"
 }
]